data2bids/__init__.py
data2bids/data2bids.py
data2bids/utils.py
data2bids-1.2.1.data/scripts/data2bids
data2bids-1.2.1.dist-info/LICENSE.txt
data2bids-1.2.1.dist-info/METADATA
data2bids-1.2.1.dist-info/WHEEL
data2bids-1.2.1.dist-info/top_level.txt
data2bids-1.2.1.dist-info/RECORD
