Metadata-Version: 2.1
Name: data2bids
Version: 1.2.1
Summary: Reorganize fmri files to make them BIDS compliant.
Home-page: https://github.com/SIMEXP/Data2Bids
Author: Loic TETREL
Author-email: loic.tetrel.pro@gmail.com
License: MIT
Platform: UNKNOWN
Requires-Dist: nibabel
Requires-Dist: numpy
